flake8_click/__init__.py
flake8_click/flake8_click.py
flake8_click-0.3.1.dist-info/entry_points.txt
flake8_click-0.3.1.dist-info/WHEEL
flake8_click-0.3.1.dist-info/METADATA
flake8_click-0.3.1.dist-info/RECORD
